{"10319 S GREEN BAY AVE": {"precinct": "31", "ward": "10"}, "10319 S EMERALD AVE": {"precinct": "20", "ward": "34"}, "10319 S ARTESIAN AVE": {"precinct": "51", "ward": "19"}, "10319 S AVENUE H": {"precinct": "29", "ward": "10"}, "10319 S AVENUE L": {"precinct": "30", "ward": "10"}, "10319 S HAMLIN AVE": {"precinct": "12", "ward": "19"}, "10319 S CALIFORNIA AVE": {"precinct": "1", "ward": "19"}, "10319 S CALHOUN AVE": {"precinct": "45", "ward": "7"}, "10319 S GREEN ST": {"precinct": "12", "ward": "34"}, "10319 S HAMILTON AVE": {"precinct": "26", "ward": "19"}, "10319 S RIDGEWAY AVE": {"precinct": "12", "ward": "19"}, "10319 S SAWYER AVE": {"precinct": "30", "ward": "19"}, "10319 S FOREST AVE": {"precinct": "5", "ward": "9"}, "10319 S RHODES AVE": {"precinct": "13", "ward": "9"}, "10319 S TROY ST": {"precinct": "6", "ward": "19"}, "10319 S CHRISTIANA AVE": {"precinct": "30", "ward": "19"}, "10319 S TRUMBULL AVE": {"precinct": "30", "ward": "19"}, "10319 S MUSKEGON AVE": {"precinct": "21", "ward": "10"}, "10319 S MILLARD AVE": {"precinct": "12", "ward": "19"}, "10319 S WALLACE ST": {"precinct": "24", "ward": "34"}, "10319 S HALE AVE": {"precinct": "36", "ward": "19"}, "10319 S EBERHART AVE": {"precinct": "14", "ward": "9"}, "10319 S KING DR": {"precinct": "5", "ward": "9"}, "10319 S CALUMET AVE": {"precinct": "5", "ward": "9"}, "10319 S SPAULDING AVE": {"precinct": "30", "ward": "19"}, "10319 S LAWNDALE AVE": {"precinct": "12", "ward": "19"}, "10319 S SAINT LOUIS AVE": {"precinct": "24", "ward": "19"}}