{"10559 S HAMLIN AVE": {"precinct": "3", "ward": "19"}, "10559 S TALMAN AVE": {"precinct": "1", "ward": "19"}, "10559 S MILLARD AVE": {"precinct": "3", "ward": "19"}, "10559 S PRAIRIE AVE": {"precinct": "40", "ward": "9"}, "10559 S HALE AVE": {"precinct": "36", "ward": "19"}, "10559 S SEELEY AVE": {"precinct": "26", "ward": "19"}, "10559 S WHIPPLE ST": {"precinct": "6", "ward": "19"}, "10559 S CAMPBELL AVE": {"precinct": "51", "ward": "19"}, "10559 S INDIANA AVE": {"precinct": "40", "ward": "9"}, "10559 S AVENUE F": {"precinct": "32", "ward": "10"}, "10559 S LAFAYETTE AVE": {"precinct": "18", "ward": "34"}, "10559 S HAMILTON AVE": {"precinct": "34", "ward": "19"}, "10559 S AVENUE H": {"precinct": "28", "ward": "10"}, "10559 S PROSPECT AVE": {"precinct": "28", "ward": "19"}, "10559 S CORLISS AVE": {"precinct": "8", "ward": "9"}, "10559 S SAINT LOUIS AVE": {"precinct": "33", "ward": "19"}, "10559 S DRAKE AVE": {"precinct": "33", "ward": "19"}, "10559 S HOMAN AVE": {"precinct": "33", "ward": "19"}, "10559 S EDBROOKE AVE": {"precinct": "29", "ward": "9"}, "10559 S CENTRAL PARK AVE": {"precinct": "33", "ward": "19"}, "10559 S STATE ST": {"precinct": "29", "ward": "9"}, "10559 S WOOD ST": {"precinct": "37", "ward": "19"}, "10559 S ALBANY AVE": {"precinct": "6", "ward": "19"}, "10559 S TROY ST": {"precinct": "29", "ward": "19"}, "10559 S AVENUE G": {"precinct": "32", "ward": "10"}, "10559 S LAWNDALE AVE": {"precinct": "3", "ward": "19"}, "10559 S SPAULDING AVE": {"precinct": "33", "ward": "19"}}