{"11937 S WALLACE ST": {"ward": "34", "precinct": "16"}, "11937 S LOWE AVE": {"ward": "34", "precinct": "31"}, "11937 S STEWART AVE": {"ward": "34", "precinct": "16"}, "11937 S CALUMET AVE": {"ward": "9", "precinct": "28"}, "11937 S HARVARD AVE": {"ward": "34", "precinct": "16"}, "11937 S STATE ST": {"ward": "9", "precinct": "11"}, "11937 S NORMAL AVE": {"ward": "34", "precinct": "16"}, "11937 S WENTWORTH AVE": {"ward": "9", "precinct": "18"}, "11937 S UNION AVE": {"ward": "34", "precinct": "31"}, "11937 S EMERALD AVE": {"ward": "34", "precinct": "31"}, "11937 S PRINCETON AVE": {"ward": "34", "precinct": "16"}}