{"2319 N CLEVELAND AVE": {"ward": "43", "precinct": "44"}, "2319 N MILWAUKEE AVE": {"ward": "1", "precinct": "19"}, "2319 W WARREN BLVD": {"ward": "27", "precinct": "17"}, "2319 W CULLERTON ST": {"ward": "25", "precinct": "8"}, "2319 N OAK PARK AVE": {"ward": "36", "precinct": "3"}, "2319 W WASHINGTON BLVD": {"ward": "27", "precinct": "17"}, "2319 W SHAKESPEARE AVE": {"ward": "32", "precinct": "29"}, "2319 N DRAKE AVE": {"ward": "35", "precinct": "7"}, "2319 S ALBANY AVE": {"ward": "12", "precinct": "22"}, "2319 W DIVERSEY AVE": {"ward": "32", "precinct": "1"}, "2319 S LEAVITT ST": {"ward": "25", "precinct": "26"}, "2319 W IOWA ST": {"ward": "1", "precinct": "12"}, "2319 S SACRAMENTO AVE": {"ward": "12", "precinct": "22"}, "2319 W MONROE ST": {"ward": "27", "precinct": "17"}, "2319 W BELDEN AVE": {"ward": "32", "precinct": "16"}, "2319 N LOWELL AVE": {"ward": "31", "precinct": "22"}, "2319 N MOBILE AVE": {"ward": "36", "precinct": "4"}, "2319 N MELVINA AVE": {"ward": "36", "precinct": "2"}, "2319 N NEWCASTLE AVE": {"ward": "36", "precinct": "3"}, "2319 S PRINCETON AVE": {"ward": "25", "precinct": "6"}, "2319 W FARRAGUT AVE": {"ward": "40", "precinct": "21"}, "2319 N HAMILTON AVE": {"ward": "32", "precinct": "37"}, "2319 W DEVON AVE": {"ward": "50", "precinct": "31"}, "2319 N KILDARE AVE": {"ward": "31", "precinct": "22"}, "2319 W MONTROSE AVE": {"ward": "47", "precinct": "14"}, "2319 N NORDICA AVE": {"ward": "29", "precinct": "23"}, "2319 N LAWNDALE AVE": {"ward": "35", "precinct": "21"}, "2319 W WABANSIA AVE": {"ward": "32", "precinct": "2"}, "2319 W 80TH PL": {"ward": "18", "precinct": "18"}, "2319 W HARRISON ST": {"ward": "28", "precinct": "46"}, "2319 N MANGO AVE": {"ward": "36", "precinct": "21"}, "2319 W CHASE AVE": {"ward": "50", "precinct": "8"}, "2319 W WAVELAND AVE": {"ward": "47", "precinct": "7"}, "2319 W DICKENS AVE": {"ward": "32", "precinct": "29"}, "2319 W 24TH ST": {"ward": "25", "precinct": "5"}, "2319 W TAYLOR ST": {"ward": "28", "precinct": "19"}, "2319 W CULLOM AVE": {"ward": "47", "precinct": "14"}, "2319 W 22ND PL": {"ward": "25", "precinct": "5"}, "2319 N KENNETH AVE": {"ward": "31", "precinct": "22"}, "2319 S AVERS AVE": {"ward": "22", "precinct": "14"}, "2319 N KEELER AVE": {"ward": "35", "precinct": "18"}, "2319 W BARRY AVE": {"ward": "32", "precinct": "9"}, "2319 N LOREL AVE": {"ward": "36", "precinct": "25"}, "2319 N MERRIMAC AVE": {"ward": "36", "precinct": "2"}, "2319 S RIDGEWAY AVE": {"ward": "22", "precinct": "14"}, "2319 S WHIPPLE ST": {"ward": "12", "precinct": "22"}, "2319 W 109TH ST": {"ward": "19", "precinct": "40"}, "2319 W 80TH ST": {"ward": "18", "precinct": "18"}, "2319 W SCHOOL ST": {"ward": "32", "precinct": "19"}, "2319 W 19TH ST": {"ward": "25", "precinct": "8"}, "2319 W 81ST PL": {"ward": "18", "precinct": "18"}, "2319 W THOMAS ST": {"ward": "1", "precinct": "15"}, "2319 E 70TH PL": {"ward": "5", "precinct": "26"}, "2319 N SPRINGFIELD AVE": {"ward": "35", "precinct": "14"}, "2319 E 103RD ST": {"ward": "7", "precinct": "45"}, "2319 W MELROSE ST": {"ward": "32", "precinct": "19"}, "2319 W ROSEMONT AVE": {"ward": "50", "precinct": "31"}, "2319 W ARTHUR AVE": {"ward": "50", "precinct": "31"}, "2319 W 72ND ST": {"ward": "18", "precinct": "5"}, "2319 N SAYRE AVE": {"ward": "36", "precinct": "27"}, "2319 S LAWNDALE AVE": {"ward": "22", "precinct": "14"}, "2319 N MAJOR AVE": {"ward": "36", "precinct": "21"}, "2319 W 114TH ST": {"ward": "19", "precinct": "20"}, "2319 N NORMANDY AVE": {"ward": "29", "precinct": "30"}, "2319 E 83RD ST": {"ward": "7", "precinct": "26"}, "2319 W 21ST ST": {"ward": "25", "precinct": "8"}, "2319 N MAPLEWOOD AVE": {"ward": "1", "precinct": "7"}, "2319 W 25TH ST": {"ward": "25", "precinct": "5"}, "2319 W ADDISON ST": {"ward": "47", "precinct": "7"}, "2319 S SAWYER AVE": {"ward": "12", "precinct": "14"}, "2319 N MENARD AVE": {"ward": "36", "precinct": "23"}, "2319 W MEDILL AVE": {"ward": "32", "precinct": "16"}, "2319 N COMMONWEALTH AVE": {"ward": "43", "precinct": "32"}, "2319 W 107TH ST": {"ward": "19", "precinct": "31"}, "2319 N GREENVIEW AVE": {"ward": "2", "precinct": "26"}, "2319 N LAMON AVE": {"ward": "36", "precinct": "9"}, "2319 N HALSTED ST": {"ward": "43", "precinct": "29"}, "2319 W MCLEAN AVE": {"ward": "32", "precinct": "29"}, "2319 W JACKSON BLVD": {"ward": "27", "precinct": "18"}, "2319 W HADDON AVE": {"ward": "1", "precinct": "14"}, "2319 W GRENSHAW ST": {"ward": "28", "precinct": "19"}, "2319 W 115TH ST": {"ward": "19", "precinct": "20"}, "2319 N LEAVITT ST": {"ward": "32", "precinct": "37"}, "2319 W 55TH ST": {"ward": "15", "precinct": "3"}, "2319 N MASON AVE": {"ward": "36", "precinct": "23"}, "2319 W 51ST ST": {"ward": "15", "precinct": "19"}, "2319 N HARDING AVE": {"ward": "35", "precinct": "14"}, "2319 W 71ST ST": {"ward": "18", "precinct": "5"}, "2319 W MARQUETTE RD": {"ward": "17", "precinct": "36"}, "2319 W ERIE ST": {"ward": "26", "precinct": "28"}, "2319 W 35TH PL": {"ward": "12", "precinct": "3"}, "2319 N AVERS AVE": {"ward": "35", "precinct": "21"}, "2319 W MORSE AVE": {"ward": "50", "precinct": "37"}, "2319 N LISTER AVE": {"ward": "32", "precinct": "37"}, "2319 W 50TH ST": {"ward": "15", "precinct": "19"}, "2319 N MCVICKER AVE": {"ward": "36", "precinct": "23"}, "2319 W WINNEMAC AVE": {"ward": "40", "precinct": "7"}, "2319 N KARLOV AVE": {"ward": "35", "precinct": "14"}, "2319 W FOSTER AVE": {"ward": "40", "precinct": "11"}, "2319 N KEATING AVE": {"ward": "36", "precinct": "11"}, "2319 N SOUTHPORT AVE": {"ward": "2", "precinct": "22"}, "2319 E 70TH ST": {"ward": "5", "precinct": "26"}, "2319 W 18TH PL": {"ward": "25", "precinct": "9"}, "2319 W OHIO ST": {"ward": "26", "precinct": "28"}, "2319 S KENNETH AVE": {"ward": "22", "precinct": "21"}, "2319 N MONTICELLO AVE": {"ward": "35", "precinct": "8"}, "2319 W 50TH PL": {"ward": "15", "precinct": "19"}, "2319 S WENTWORTH AVE": {"ward": "25", "precinct": "6"}, "2319 W 91ST ST": {"ward": "19", "precinct": "5"}, "2319 N SACRAMENTO AVE": {"ward": "1", "precinct": "19"}, "2319 E 73RD ST": {"ward": "7", "precinct": "4"}, "2319 N ROCKWELL ST": {"ward": "1", "precinct": "7"}, "2319 N KILBOURN AVE": {"ward": "31", "precinct": "22"}, "2319 N BOSWORTH AVE": {"ward": "2", "precinct": "26"}, "2319 N KEDZIE AVE": {"ward": "32", "precinct": "20"}, "2319 W 47TH PL": {"ward": "15", "precinct": "19"}, "2319 N NATCHEZ AVE": {"ward": "36", "precinct": "4"}, "2319 W WALTON ST": {"ward": "1", "precinct": "12"}, "2319 N LOCKWOOD AVE": {"ward": "36", "precinct": "25"}, "2319 W 107TH PL": {"ward": "19", "precinct": "31"}, "2319 S OAKLEY AVE": {"ward": "25", "precinct": "5"}, "2319 N WAYNE AVE": {"ward": "2", "precinct": "22"}}