{"2328 W LUNT AVE": {"ward": "50", "precinct": "7"}, "2328 W BELMONT AVE": {"ward": "32", "precinct": "19"}, "2328 N RIDGEWAY AVE": {"ward": "35", "precinct": "21"}, "2328 E 70TH ST": {"ward": "5", "precinct": "29"}, "2328 W JACKSON BLVD": {"ward": "27", "precinct": "18"}, "2328 N GREENVIEW AVE": {"ward": "2", "precinct": "26"}, "2328 S SAWYER AVE": {"ward": "12", "precinct": "16"}, "2328 W 112TH PL": {"ward": "19", "precinct": "14"}, "2328 N MAJOR AVE": {"ward": "36", "precinct": "21"}, "2328 N MILWAUKEE AVE": {"ward": "1", "precinct": "19"}, "2328 W 21ST PL": {"ward": "25", "precinct": "8"}, "2328 S KOSTNER AVE": {"ward": "22", "precinct": "21"}, "2328 W CHARLESTON ST": {"ward": "32", "precinct": "29"}, "2328 S CENTRAL PARK AVE": {"ward": "22", "precinct": "14"}, "2328 W RICE ST": {"ward": "1", "precinct": "12"}, "2328 W 25TH ST": {"ward": "25", "precinct": "5"}, "2328 N HAMLIN AVE": {"ward": "35", "precinct": "21"}, "2328 W ARGYLE ST": {"ward": "40", "precinct": "7"}, "2328 W SUPERIOR ST": {"ward": "1", "precinct": "12"}, "2328 W 107TH PL": {"ward": "19", "precinct": "31"}, "2328 N KENNETH AVE": {"ward": "31", "precinct": "22"}, "2328 N MERRIMAC AVE": {"ward": "36", "precinct": "4"}, "2328 N SPRINGFIELD AVE": {"ward": "35", "precinct": "14"}, "2328 N MCVICKER AVE": {"ward": "36", "precinct": "2"}, "2328 W GREENLEAF AVE": {"ward": "50", "precinct": "7"}, "2328 N CLEVELAND AVE": {"ward": "43", "precinct": "20"}, "2328 W 24TH ST": {"ward": "25", "precinct": "5"}, "2328 N MONTICELLO AVE": {"ward": "35", "precinct": "21"}, "2328 N MEADE AVE": {"ward": "36", "precinct": "2"}, "2328 W 18TH PL": {"ward": "25", "precinct": "9"}, "2328 N AUSTIN AVE": {"ward": "36", "precinct": "23"}, "2328 N KEYSTONE AVE": {"ward": "35", "precinct": "14"}, "2328 W PRATT BLVD": {"ward": "50", "precinct": "37"}, "2328 N LINCOLN PARK W": {"ward": "43", "precinct": "32"}, "2328 E 70TH PL": {"ward": "5", "precinct": "26"}, "2328 W WOLFRAM ST": {"ward": "32", "precinct": "1"}, "2328 N MARMORA AVE": {"ward": "36", "precinct": "23"}, "2328 W MELROSE ST": {"ward": "32", "precinct": "19"}, "2328 W 23RD ST": {"ward": "25", "precinct": "5"}, "2328 S AVERS AVE": {"ward": "22", "precinct": "14"}, "2328 W OHIO ST": {"ward": "26", "precinct": "28"}, "2328 N MANGO AVE": {"ward": "36", "precinct": "21"}, "2328 N PARKSIDE AVE": {"ward": "36", "precinct": "21"}, "2328 N NEWCASTLE AVE": {"ward": "36", "precinct": "27"}, "2328 W AUGUSTA BLVD": {"ward": "1", "precinct": "12"}, "2328 W MORSE AVE": {"ward": "50", "precinct": "37"}, "2328 N LOCKWOOD AVE": {"ward": "36", "precinct": "25"}, "2328 N ROCKWELL ST": {"ward": "1", "precinct": "16"}, "2328 N HAMILTON AVE": {"ward": "32", "precinct": "37"}, "2328 W ERIE ST": {"ward": "1", "precinct": "12"}, "2328 W WILSON AVE": {"ward": "47", "precinct": "42"}, "2328 W THOMAS ST": {"ward": "1", "precinct": "14"}, "2328 W 22ND PL": {"ward": "25", "precinct": "5"}, "2328 W 80TH PL": {"ward": "18", "precinct": "18"}, "2328 S WHIPPLE ST": {"ward": "12", "precinct": "22"}, "2328 W CULLERTON ST": {"ward": "25", "precinct": "8"}, "2328 W 24TH PL": {"ward": "25", "precinct": "5"}, "2328 W 108TH PL": {"ward": "19", "precinct": "31"}, "2328 W 19TH ST": {"ward": "25", "precinct": "9"}, "2328 E 96TH ST": {"ward": "7", "precinct": "40"}, "2328 N OAKLEY AVE": {"ward": "32", "precinct": "16"}, "2328 N AVERS AVE": {"ward": "35", "precinct": "14"}, "2328 S TRUMBULL AVE": {"ward": "22", "precinct": "22"}, "2328 N MAPLEWOOD AVE": {"ward": "1", "precinct": "7"}, "2328 W 80TH ST": {"ward": "18", "precinct": "18"}, "2328 N RUTHERFORD AVE": {"ward": "36", "precinct": "3"}, "2328 N LARAMIE AVE": {"ward": "36", "precinct": "25"}, "2328 N JANSSEN AVE": {"ward": "2", "precinct": "26"}, "2328 W 111TH PL": {"ward": "19", "precinct": "14"}, "2328 S ALBANY AVE": {"ward": "12", "precinct": "14"}, "2328 W FARWELL AVE": {"ward": "50", "precinct": "37"}, "2328 W 81ST ST": {"ward": "18", "precinct": "18"}, "2328 N NORMANDY AVE": {"ward": "36", "precinct": "3"}, "2328 N LAKEWOOD AVE": {"ward": "2", "precinct": "22"}, "2328 W WARREN BLVD": {"ward": "27", "precinct": "17"}, "2328 N SPAULDING AVE": {"ward": "35", "precinct": "10"}, "2328 S KIRKLAND AVE": {"ward": "22", "precinct": "21"}, "2328 N KOSTNER AVE": {"ward": "31", "precinct": "22"}, "2328 W WALTON ST": {"ward": "1", "precinct": "12"}, "2328 W JARVIS AVE": {"ward": "50", "precinct": "8"}, "2328 W MEDILL AVE": {"ward": "32", "precinct": "16"}, "2328 W WASHINGTON BLVD": {"ward": "27", "precinct": "43"}, "2328 N SOUTHPORT AVE": {"ward": "2", "precinct": "26"}, "2328 W IOWA ST": {"ward": "1", "precinct": "12"}, "2328 S KEDZIE AVE": {"ward": "12", "precinct": "14"}, "2328 N MELVINA AVE": {"ward": "36", "precinct": "2"}, "2328 N LAWNDALE AVE": {"ward": "35", "precinct": "21"}, "2328 W FARRAGUT AVE": {"ward": "40", "precinct": "21"}, "2328 N KILPATRICK AVE": {"ward": "36", "precinct": "11"}, "2328 W MCLEAN AVE": {"ward": "32", "precinct": "29"}, "2328 S MARSHALL BLVD": {"ward": "12", "precinct": "22"}, "2328 S HAMLIN AVE": {"ward": "22", "precinct": "14"}, "2328 W BIRCHWOOD AVE": {"ward": "49", "precinct": "21"}}