{"2923 S EMERALD AVE": {"ward": "11", "precinct": "16"}, "2923 W JARVIS AVE": {"ward": "50", "precinct": "3"}, "2923 W MORSE AVE": {"ward": "50", "precinct": "11"}, "2923 N MEADE AVE": {"ward": "30", "precinct": "13"}, "2923 W 25TH PL": {"ward": "12", "precinct": "18"}, "2923 N NASHVILLE AVE": {"ward": "36", "precinct": "10"}, "2923 N KENNETH AVE": {"ward": "31", "precinct": "26"}, "2923 W PERSHING RD": {"ward": "12", "precinct": "20"}, "2923 N TROY ST": {"ward": "33", "precinct": "28"}, "2923 N LOTUS AVE": {"ward": "31", "precinct": "3"}, "2923 S NORMAL AVE": {"ward": "11", "precinct": "18"}, "2923 N KOSTNER AVE": {"ward": "31", "precinct": "26"}, "2923 E 97TH ST": {"ward": "10", "precinct": "21"}, "2923 N LINDER AVE": {"ward": "31", "precinct": "3"}, "2923 N SPRINGFIELD AVE": {"ward": "30", "precinct": "18"}, "2923 W WARREN BLVD": {"ward": "27", "precinct": "49"}, "2923 W LYNDALE ST": {"ward": "1", "precinct": "19"}, "2923 N WHIPPLE ST": {"ward": "33", "precinct": "26"}, "2923 N NORMANDY AVE": {"ward": "36", "precinct": "19"}, "2923 N CLAREMONT AVE": {"ward": "32", "precinct": "1"}, "2923 N LONG AVE": {"ward": "31", "precinct": "19"}, "2923 E 78TH ST": {"ward": "7", "precinct": "14"}, "2923 N DAMEN AVE": {"ward": "32", "precinct": "38"}, "2923 E 96TH ST": {"ward": "10", "precinct": "6"}, "2923 S LOOMIS ST": {"ward": "11", "precinct": "9"}, "2923 N RUTHERFORD AVE": {"ward": "36", "precinct": "19"}, "2923 N NEENAH AVE": {"ward": "36", "precinct": "10"}, "2923 N ELSTON AVE": {"ward": "33", "precinct": "5"}, "2923 N PARKSIDE AVE": {"ward": "31", "precinct": "15"}, "2923 N ALBANY AVE": {"ward": "33", "precinct": "26"}, "2923 W FARGO AVE": {"ward": "50", "precinct": "3"}, "2923 S BONFIELD ST": {"ward": "11", "precinct": "4"}, "2923 S ARCH ST": {"ward": "11", "precinct": "9"}, "2923 N HARDING AVE": {"ward": "30", "precinct": "18"}, "2923 S CANAL ST": {"ward": "11", "precinct": "18"}, "2923 N OAK PARK AVE": {"ward": "36", "precinct": "19"}, "2923 N MULLIGAN AVE": {"ward": "30", "precinct": "16"}, "2923 N DAWSON AVE": {"ward": "35", "precinct": "11"}, "2923 N MANGO AVE": {"ward": "30", "precinct": "12"}, "2923 N KOLMAR AVE": {"ward": "31", "precinct": "5"}, "2923 S HAYNES CT": {"ward": "11", "precinct": "9"}, "2923 N TALMAN AVE": {"ward": "33", "precinct": "5"}, "2923 W CATALPA AVE": {"ward": "40", "precinct": "30"}, "2923 W DIVERSEY AVE": {"ward": "32", "precinct": "17"}, "2923 N MENARD AVE": {"ward": "30", "precinct": "12"}, "2923 W WILSON AVE": {"ward": "33", "precinct": "8"}, "2923 N KILDARE AVE": {"ward": "31", "precinct": "26"}, "2923 W ADAMS ST": {"ward": "27", "precinct": "14"}, "2923 W FULTON ST": {"ward": "27", "precinct": "36"}, "2923 W 36TH ST": {"ward": "12", "precinct": "2"}, "2923 N ALLEN AVE": {"ward": "35", "precinct": "11"}, "2923 W 24TH BLVD": {"ward": "12", "precinct": "18"}, "2923 N SPAULDING AVE": {"ward": "35", "precinct": "1"}, "2923 W 39TH PL": {"ward": "12", "precinct": "20"}, "2923 W ARGYLE ST": {"ward": "40", "precinct": "17"}, "2923 E 78TH PL": {"ward": "7", "precinct": "21"}, "2923 W WALNUT ST": {"ward": "27", "precinct": "4"}, "2923 N KILPATRICK AVE": {"ward": "31", "precinct": "30"}, "2923 S ELIAS CT": {"ward": "11", "precinct": "9"}, "2923 N MOODY AVE": {"ward": "30", "precinct": "13"}, "2923 N MAJOR AVE": {"ward": "31", "precinct": "15"}, "2923 W BELMONT AVE": {"ward": "33", "precinct": "13"}, "2923 S LOWE AVE": {"ward": "11", "precinct": "16"}, "2923 W SUMMERDALE AVE": {"ward": "40", "precinct": "34"}, "2923 N NATOMA AVE": {"ward": "36", "precinct": "19"}, "2923 N KILBOURN AVE": {"ward": "31", "precinct": "26"}, "2923 W 56TH ST": {"ward": "16", "precinct": "1"}, "2923 N GRESHAM AVE": {"ward": "35", "precinct": "6"}, "2923 W 38TH ST": {"ward": "12", "precinct": "12"}, "2923 N WISNER AVE": {"ward": "35", "precinct": "11"}, "2923 N NEW ENGLAND AVE": {"ward": "36", "precinct": "29"}, "2923 W NELSON ST": {"ward": "33", "precinct": "13"}, "2923 N RIDGEWAY AVE": {"ward": "30", "precinct": "24"}, "2923 W WILCOX ST": {"ward": "27", "precinct": "49"}, "2923 W 25TH ST": {"ward": "12", "precinct": "18"}, "2923 S ARCHER AVE": {"ward": "11", "precinct": "9"}, "2923 W LUNT AVE": {"ward": "50", "precinct": "11"}, "2923 N CLYBOURN AVE": {"ward": "32", "precinct": "38"}, "2923 N MERRIMAC AVE": {"ward": "30", "precinct": "16"}, "2923 N MASON AVE": {"ward": "30", "precinct": "12"}, "2923 N FAIRFIELD AVE": {"ward": "33", "precinct": "19"}, "2923 W BERWYN AVE": {"ward": "40", "precinct": "34"}, "2923 N KEATING AVE": {"ward": "31", "precinct": "30"}, "2923 W ROSEMONT AVE": {"ward": "50", "precinct": "17"}, "2923 W JEROME ST": {"ward": "50", "precinct": "3"}, "2923 W FLOURNOY ST": {"ward": "28", "precinct": "35"}, "2923 S PARNELL AVE": {"ward": "11", "precinct": "18"}, "2923 W BIRCHWOOD AVE": {"ward": "50", "precinct": "3"}, "2923 N MILWAUKEE AVE": {"ward": "35", "precinct": "11"}, "2923 N LUNA AVE": {"ward": "31", "precinct": "3"}, "2923 N NAGLE AVE": {"ward": "36", "precinct": "10"}, "2923 W ARTHINGTON ST": {"ward": "28", "precinct": "35"}, "2923 N MARMORA AVE": {"ward": "30", "precinct": "12"}, "2923 N SEELEY AVE": {"ward": "32", "precinct": "38"}, "2923 S SHIELDS AVE": {"ward": "11", "precinct": "14"}, "2923 W BALMORAL AVE": {"ward": "40", "precinct": "34"}, "2923 N KEDZIE AVE": {"ward": "33", "precinct": "28"}, "2923 W SHERWIN AVE": {"ward": "50", "precinct": "1"}, "2923 N LOWELL AVE": {"ward": "31", "precinct": "26"}, "2923 N NEWLAND AVE": {"ward": "36", "precinct": "29"}, "2923 N WASHTENAW AVE": {"ward": "33", "precinct": "19"}, "2923 N NEWCASTLE AVE": {"ward": "36", "precinct": "19"}, "2923 W 40TH ST": {"ward": "12", "precinct": "20"}, "2923 N RACINE AVE": {"ward": "44", "precinct": "40"}, "2923 N NATCHEZ AVE": {"ward": "36", "precinct": "10"}, "2923 S UNION AVE": {"ward": "11", "precinct": "16"}, "2923 N CICERO AVE": {"ward": "31", "precinct": "30"}}