{"3724  W 86TH ST": {"precinct": "7", "ward": "18"}, "3724  S WOLCOTT AVE": {"precinct": "4", "ward": "12"}, "3724  N NORDICA AVE": {"precinct": "3", "ward": "38"}, "3724  W 56TH ST": {"precinct": "9", "ward": "23"}, "3724  W SHAKESPEARE AVE": {"precinct": "3", "ward": "35"}, "3724  N LAWNDALE AVE": {"precinct": "1", "ward": "45"}, "3724  E 112TH ST": {"precinct": "10", "ward": "10"}, "3724  W 59TH PL": {"precinct": "5", "ward": "23"}, "3724  W 71ST ST": {"precinct": "47", "ward": "13"}, "3724  N LOCKWOOD AVE": {"precinct": "16", "ward": "36"}, "3724  W GRAND AVE": {"precinct": "43", "ward": "26"}, "3724  W 86TH PL": {"precinct": "7", "ward": "18"}, "3724  W 66TH ST": {"precinct": "30", "ward": "13"}, "3724  N HERMITAGE AVE": {"precinct": "43", "ward": "47"}, "3724  N CLAREMONT AVE": {"precinct": "46", "ward": "47"}, "3724  W 82ND PL": {"precinct": "29", "ward": "18"}, "3724  W 77TH PL": {"precinct": "2", "ward": "18"}, "3724  N JANSSEN AVE": {"precinct": "16", "ward": "44"}, "3724  S PARNELL AVE": {"precinct": "29", "ward": "11"}, "3724  W SUNNYSIDE AVE": {"precinct": "9", "ward": "35"}, "3724  W 57TH ST": {"precinct": "33", "ward": "23"}, "3724  S MICHIGAN AVE": {"precinct": "23", "ward": "3"}, "3724  W 85TH PL": {"precinct": "7", "ward": "18"}, "3724  W DIVERSEY AVE": {"precinct": "24", "ward": "30"}, "3724  N BERNARD ST": {"precinct": "4", "ward": "35"}, "3724  W 54TH ST": {"precinct": "9", "ward": "23"}, "3724  W 65TH ST": {"precinct": "11", "ward": "23"}, "3724  W 55TH PL": {"precinct": "9", "ward": "23"}, "3724  N PITTSBURGH AVE": {"precinct": "20", "ward": "38"}, "3724  W 60TH PL": {"precinct": "7", "ward": "23"}, "3724  W FERDINAND ST": {"precinct": "23", "ward": "27"}, "3724  N MOZART ST": {"precinct": "22", "ward": "33"}, "3724  W 62ND ST": {"precinct": "32", "ward": "23"}, "3724  N SOUTHPORT AVE": {"precinct": "25", "ward": "44"}, "3724  W 65TH PL": {"precinct": "11", "ward": "23"}, "3724  N ORIOLE AVE": {"precinct": "27", "ward": "38"}, "3724  W 70TH ST": {"precinct": "47", "ward": "13"}, "3724  W 105TH ST": {"precinct": "12", "ward": "19"}, "3724  W PALMER ST": {"precinct": "3", "ward": "35"}, "3724  W 63RD PL": {"precinct": "32", "ward": "23"}, "3724  N SAYRE AVE": {"precinct": "16", "ward": "38"}, "3724  N MILWAUKEE AVE": {"precinct": "6", "ward": "45"}, "3724  N SPAULDING AVE": {"precinct": "16", "ward": "33"}, "3724  N NEVA AVE": {"precinct": "3", "ward": "38"}, "3724  W 80TH ST": {"precinct": "17", "ward": "18"}, "3724  N CICERO AVE": {"precinct": "1", "ward": "30"}, "3724  N OAK PARK AVE": {"precinct": "16", "ward": "38"}, "3724  W EASTWOOD AVE": {"precinct": "30", "ward": "35"}, "3724  W DICKENS AVE": {"precinct": "3", "ward": "35"}, "3724  N SAINT LOUIS AVE": {"precinct": "4", "ward": "35"}, "3724  W 81ST PL": {"precinct": "29", "ward": "18"}, "3724  N ODELL AVE": {"precinct": "29", "ward": "38"}, "3724  S UNION AVE": {"precinct": "24", "ward": "11"}, "3724  W 107TH ST": {"precinct": "3", "ward": "19"}, "3724  W 78TH PL": {"precinct": "2", "ward": "18"}, "3724  W 59TH ST": {"precinct": "5", "ward": "23"}, "3724  W 115TH ST": {"precinct": "11", "ward": "19"}, "3724  N DRAKE AVE": {"precinct": "4", "ward": "35"}, "3724  W WRIGHTWOOD AVE": {"precinct": "7", "ward": "31"}, "3724  N SHEFFIELD AVE": {"precinct": "31", "ward": "44"}, "3724  N NORA AVE": {"precinct": "16", "ward": "38"}, "3724  W 83RD PL": {"precinct": "29", "ward": "18"}, "3724  N OSCEOLA AVE": {"precinct": "29", "ward": "38"}, "3724  W LELAND AVE": {"precinct": "30", "ward": "35"}, "3724  W 62ND PL": {"precinct": "32", "ward": "23"}, "3724  W LEXINGTON ST": {"precinct": "4", "ward": "24"}, "3724  W WINDSOR AVE": {"precinct": "9", "ward": "35"}, "3724  N KENNETH AVE": {"precinct": "6", "ward": "45"}, "3724  W 70TH PL": {"precinct": "47", "ward": "13"}, "3724  N PACIFIC AVE": {"precinct": "17", "ward": "38"}, "3724  N LEAVITT ST": {"precinct": "2", "ward": "47"}, "3724  W CORTLAND ST": {"precinct": "26", "ward": "1"}, "3724  N PLAINFIELD AVE": {"precinct": "20", "ward": "38"}, "3724  N BOSWORTH AVE": {"precinct": "16", "ward": "44"}, "3724  W 56TH PL": {"precinct": "33", "ward": "23"}, "3724  W 67TH PL": {"precinct": "44", "ward": "13"}, "3724  W 61ST ST": {"precinct": "32", "ward": "23"}, "3724  W CERMAK RD": {"precinct": "3", "ward": "24"}, "3724  N OKETO AVE": {"precinct": "29", "ward": "38"}, "3724  N HARLEM AVE": {"precinct": "29", "ward": "38"}, "3724  N CLARK ST": {"precinct": "32", "ward": "44"}, "3724  S HERMITAGE AVE": {"precinct": "19", "ward": "12"}, "3724  W 13TH ST": {"precinct": "5", "ward": "24"}, "3724  N RUTHERFORD AVE": {"precinct": "8", "ward": "38"}, "3724  S WOOD ST": {"precinct": "1", "ward": "12"}, "3724  N FREMONT ST": {"precinct": "10", "ward": "46"}, "3724  W 104TH ST": {"precinct": "12", "ward": "19"}, "3724  N NEWCASTLE AVE": {"precinct": "16", "ward": "38"}, "3724  N KEELER AVE": {"precinct": "5", "ward": "45"}, "3724  N OLCOTT AVE": {"precinct": "6", "ward": "38"}, "3724  S INDIANA AVE": {"precinct": "35", "ward": "3"}, "3724  W DOUGLAS BLVD": {"precinct": "24", "ward": "24"}, "3724  N BELL AVE": {"precinct": "2", "ward": "47"}, "3724  W 80TH PL": {"precinct": "17", "ward": "18"}, "3724  N OLEANDER AVE": {"precinct": "27", "ward": "38"}, "3724  N NEW ENGLAND AVE": {"precinct": "16", "ward": "38"}, "3724  W DIVISION ST": {"precinct": "24", "ward": "27"}, "3724  W CORNELIA AVE": {"precinct": "32", "ward": "30"}, "3724  N OCONTO AVE": {"precinct": "29", "ward": "38"}, "3724  N RACINE AVE": {"precinct": "32", "ward": "44"}, "3724  N MAGNOLIA AVE": {"precinct": "32", "ward": "44"}, "3724  N PAGE AVE": {"precinct": "17", "ward": "38"}, "3724  W 69TH PL": {"precinct": "47", "ward": "13"}, "3724  W MONTROSE AVE": {"precinct": "22", "ward": "35"}, "3724  N SAWYER AVE": {"precinct": "16", "ward": "33"}, "3724  N MARSHFIELD AVE": {"precinct": "33", "ward": "47"}, "3724  N TROY ST": {"precinct": "12", "ward": "33"}, "3724  W LYNDALE ST": {"precinct": "21", "ward": "35"}, "3724  W 64TH PL": {"precinct": "11", "ward": "23"}, "3724  N PARIS AVE": {"precinct": "17", "ward": "38"}, "3724  W 87TH ST": {"precinct": "7", "ward": "18"}, "3724  W 66TH PL": {"precinct": "30", "ward": "13"}, "3724  W FULLERTON AVE": {"precinct": "16", "ward": "31"}, "3724  N PINE GROVE AVE": {"precinct": "10", "ward": "46"}}