{"4523 N PULASKI RD": {"ward": "35", "precinct": "9"}, "4523 S EMERALD AVE": {"ward": "11", "precinct": "13"}, "4523 S TALMAN AVE": {"ward": "15", "precinct": "4"}, "4523 N GREENVIEW AVE": {"ward": "47", "precinct": "41"}, "4523 W MONTANA ST": {"ward": "31", "precinct": "1"}, "4523 N KARLOV AVE": {"ward": "39", "precinct": "31"}, "4523 N KIMBALL AVE": {"ward": "33", "precinct": "15"}, "4523 N KENNETH": {"ward": "39", "precinct": "17"}, "4523 N ARTESIAN AVE": {"ward": "47", "precinct": "13"}, "4523 N CHRISTIANA AVE": {"ward": "33", "precinct": "20"}, "4523 S WALLACE ST": {"ward": "11", "precinct": "12"}, "4523 W ALTGELD ST": {"ward": "31", "precinct": "18"}, "4523 S FRANCISCO AVE": {"ward": "15", "precinct": "12"}, "4523 S HONORE ST": {"ward": "15", "precinct": "5"}, "4523 S SAINT LOUIS AVE": {"ward": "14", "precinct": "10"}, "4523 W 84TH PL": {"ward": "18", "precinct": "44"}, "4523 W THOMAS ST": {"ward": "37", "precinct": "21"}, "4523 N SAWYER AVE": {"ward": "33", "precinct": "20"}, "4523 S MOZART ST": {"ward": "15", "precinct": "12"}, "4523 N HAMILTON AVE": {"ward": "47", "precinct": "22"}, "4523 W PARKER AVE": {"ward": "31", "precinct": "13"}, "4523 S UNION AVE": {"ward": "11", "precinct": "13"}, "4523 W SCHUBERT AVE": {"ward": "31", "precinct": "13"}, "4523 S TROY ST": {"ward": "14", "precinct": "31"}, "4523 N KEOKUK AVE": {"ward": "39", "precinct": "19"}, "4523 S CHRISTIANA AVE": {"ward": "14", "precinct": "10"}, "4523 W WEST END AVE": {"ward": "28", "precinct": "33"}, "4523 S GREENWOOD AVE": {"ward": "4", "precinct": "10"}, "4523 S FORRESTVILLE AVE": {"ward": "3", "precinct": "4"}, "4523 S VINCENNES AVE": {"ward": "3", "precinct": "4"}, "4523 N MAGNOLIA AVE": {"ward": "46", "precinct": "25"}, "4523 S HALSTED ST": {"ward": "11", "precinct": "13"}, "4523 S PAULINA ST": {"ward": "15", "precinct": "1"}, "4523 W CONGRESS PKWY": {"ward": "28", "precinct": "16"}, "4523 S WHIPPLE ST": {"ward": "15", "precinct": "12"}, "4523 N TROY ST": {"ward": "33", "precinct": "20"}, "4523 N MASON AVE": {"ward": "38", "precinct": "36"}, "4523 N LAPORTE AVE": {"ward": "45", "precinct": "15"}, "4523 S DREXEL BLVD": {"ward": "4", "precinct": "34"}, "4523 N SAINT LOUIS AVE": {"ward": "33", "precinct": "1"}, "4523 W SCHOOL ST": {"ward": "30", "precinct": "31"}, "4523 N KENNETH AVE": {"ward": "39", "precinct": "17"}, "4523 N KILDARE AVE": {"ward": "39", "precinct": "19"}, "4523 W IRVING PARK RD": {"ward": "45", "precinct": "7"}, "4523 S FAIRFIELD AVE": {"ward": "15", "precinct": "6"}, "4523 W WASHINGTON BLVD": {"ward": "28", "precinct": "33"}, "4523 S ELLIS AVE": {"ward": "4", "precinct": "34"}, "4523 S RICHMOND ST": {"ward": "15", "precinct": "12"}, "4523 N CENTRAL PARK AVE": {"ward": "33", "precinct": "1"}, "4523 N CAMPBELL AVE": {"ward": "47", "precinct": "13"}, "4523 S CHAMPLAIN AVE": {"ward": "4", "precinct": "29"}, "4523 N DOVER ST": {"ward": "46", "precinct": "12"}, "4523 N MONITOR AVE": {"ward": "38", "precinct": "36"}, "4523 S WASHTENAW AVE": {"ward": "15", "precinct": "6"}, "4523 S LAFLIN ST": {"ward": "15", "precinct": "1"}, "4523 N MARMORA AVE": {"ward": "38", "precinct": "36"}, "4523 W 55TH ST": {"ward": "13", "precinct": "7"}, "4523 N WHIPPLE ST": {"ward": "33", "precinct": "8"}, "4523 S SACRAMENTO AVE": {"ward": "15", "precinct": "12"}, "4523 S MARSHFIELD AVE": {"ward": "15", "precinct": "1"}, "4523 S CALIFORNIA AVE": {"ward": "15", "precinct": "6"}, "4523 S ALBANY AVE": {"ward": "15", "precinct": "10"}, "4523 W JACKSON BLVD": {"ward": "28", "precinct": "16"}, "4523 N LOWELL AVE": {"ward": "39", "precinct": "19"}, "4523 W DEMING PL": {"ward": "31", "precinct": "18"}, "4523 N MELVINA AVE": {"ward": "38", "precinct": "14"}, "4523 N PAULINA ST": {"ward": "47", "precinct": "34"}, "4523 S LA CROSSE AVE": {"ward": "22", "precinct": "1"}, "4523 N SPAULDING AVE": {"ward": "33", "precinct": "20"}, "4523 N WOLCOTT AVE": {"ward": "47", "precinct": "36"}, "4523 N DRAKE AVE": {"ward": "33", "precinct": "1"}}