{"5702 S KEELER AVE": {"precinct": "24", "ward": "13"}, "5702 N HERMITAGE AVE": {"precinct": "22", "ward": "40"}, "5702 S LOOMIS ST": {"precinct": "5", "ward": "16"}, "5702 W PATTERSON AVE": {"precinct": "14", "ward": "36"}, "5702 S ALBANY AVE": {"precinct": "5", "ward": "14"}, "5702 N LEONARD AVE": {"precinct": "24", "ward": "39"}, "5702 W HENDERSON ST": {"precinct": "20", "ward": "36"}, "5702 N NEWARK AVE": {"precinct": "26", "ward": "41"}, "5702 N MELVINA AVE": {"precinct": "43", "ward": "45"}, "5702 S RACINE AVE": {"precinct": "14", "ward": "16"}, "5702 N MENARD AVE": {"precinct": "41", "ward": "45"}, "5702 N MANTON AVE": {"precinct": "24", "ward": "39"}, "5702 S INDIANA AVE": {"precinct": "31", "ward": "20"}, "5702 S SACRAMENTO AVE": {"precinct": "5", "ward": "14"}, "5702 N AVONDALE AVE": {"precinct": "26", "ward": "41"}, "5702 W 65TH ST": {"precinct": "45", "ward": "13"}, "5702 S NEVA AVE": {"precinct": "1", "ward": "23"}, "5702 S MASON AVE": {"precinct": "38", "ward": "23"}, "5702 S JUSTINE ST": {"precinct": "5", "ward": "16"}, "5702 N PARKSIDE AVE": {"precinct": "39", "ward": "45"}, "5702 S WASHTENAW AVE": {"precinct": "23", "ward": "16"}, "5702 N MAPLEWOOD AVE": {"precinct": "2", "ward": "40"}, "5702 W WASHINGTON BLVD": {"precinct": "21", "ward": "29"}, "5702 S SEELEY AVE": {"precinct": "3", "ward": "15"}, "5702 S SPAULDING AVE": {"precinct": "13", "ward": "23"}, "5702 S PARKSIDE AVE": {"precinct": "29", "ward": "23"}, "5702 W 64TH PL": {"precinct": "45", "ward": "13"}, "5702 W CHICAGO AVE": {"precinct": "35", "ward": "29"}, "5702 S SAINT LOUIS AVE": {"precinct": "34", "ward": "23"}, "5702 N KIMBALL AVE": {"precinct": "16", "ward": "39"}, "5702 S TALMAN AVE": {"precinct": "23", "ward": "16"}, "5702 W LELAND AVE": {"precinct": "18", "ward": "45"}, "5702 W DAKIN ST": {"precinct": "23", "ward": "38"}, "5702 W RACE AVE": {"precinct": "33", "ward": "29"}, "5702 S MICHIGAN AVE": {"precinct": "31", "ward": "20"}, "5702 W WILSON AVE": {"precinct": "22", "ward": "38"}, "5702 S BLACKSTONE AVE": {"precinct": "34", "ward": "5"}, "5702 S THROOP ST": {"precinct": "14", "ward": "16"}, "5702 S DAMEN AVE": {"precinct": "21", "ward": "15"}, "5702 S WABASH AVE": {"precinct": "31", "ward": "20"}, "5702 W EASTWOOD AVE": {"precinct": "18", "ward": "45"}, "5702 W 58TH ST": {"precinct": "29", "ward": "23"}, "5702 S MASSASOIT AVE": {"precinct": "4", "ward": "23"}}