{"6149 S RUTHERFORD AVE": {"ward": "13", "precinct": "38"}, "6149 S KARLOV AVE": {"ward": "23", "precinct": "30"}, "6149 W 63RD ST": {"ward": "13", "precinct": "4"}, "6149 S CARPENTER ST": {"ward": "16", "precinct": "27"}, "6149 W ROSCOE ST": {"ward": "36", "precinct": "18"}, "6149 S NARRAGANSETT AVE": {"ward": "13", "precinct": "18"}, "6149 S KING DR": {"ward": "20", "precinct": "19"}, "6149 S KILDARE AVE": {"ward": "13", "precinct": "16"}, "6149 S FRANCISCO AVE": {"ward": "16", "precinct": "13"}, "6149 W DAKIN ST": {"ward": "38", "precinct": "37"}, "6149 N SAINT LOUIS AVE": {"ward": "50", "precinct": "25"}, "6149 N KILPATRICK AVE": {"ward": "39", "precinct": "15"}, "6149 S EBERHART AVE": {"ward": "20", "precinct": "3"}, "6149 W WAVELAND AVE": {"ward": "36", "precinct": "15"}, "6149 S RHODES AVE": {"ward": "20", "precinct": "3"}, "6149 S KOLIN AVE": {"ward": "13", "precinct": "23"}, "6149 W GUNNISON ST": {"ward": "38", "precinct": "25"}, "6149 S DAMEN AVE": {"ward": "16", "precinct": "3"}, "6149 W LELAND AVE": {"ward": "38", "precinct": "25"}, "6149 W MONTROSE AVE": {"ward": "38", "precinct": "15"}, "6149 S WHIPPLE ST": {"ward": "16", "precinct": "35"}, "6149 W THORNDALE AVE": {"ward": "45", "precinct": "42"}, "6149 N KEELER AVE": {"ward": "39", "precinct": "26"}, "6149 S KOSTNER AVE": {"ward": "13", "precinct": "23"}, "6149 S EVANS AVE": {"ward": "20", "precinct": "1"}, "6149 S SPAULDING AVE": {"ward": "23", "precinct": "17"}, "6149 N MONTICELLO AVE": {"ward": "50", "precinct": "24"}, "6149 W 64TH ST": {"ward": "13", "precinct": "4"}, "6149 N LENOX AVE": {"ward": "39", "precinct": "45"}, "6149 N KIMBALL AVE": {"ward": "50", "precinct": "25"}, "6149 S GREENWOOD AVE": {"ward": "20", "precinct": "24"}, "6149 N ROCKWELL ST": {"ward": "40", "precinct": "4"}, "6149 W SCHOOL ST": {"ward": "30", "precinct": "21"}, "6149 S DREXEL AVE": {"ward": "20", "precinct": "16"}, "6149 S KOMENSKY AVE": {"ward": "23", "precinct": "30"}, "6149 W 59TH ST": {"ward": "13", "precinct": "22"}, "6149 S TRIPP AVE": {"ward": "13", "precinct": "16"}, "6149 S WOODLAWN AVE": {"ward": "20", "precinct": "34"}, "6149 S MELVINA AVE": {"ward": "13", "precinct": "11"}, "6149 N MELVINA AVE": {"ward": "39", "precinct": "20"}, "6149 N WOLCOTT AVE": {"ward": "40", "precinct": "35"}, "6149 S MOODY AVE": {"ward": "13", "precinct": "11"}, "6149 S KNOX AVE": {"ward": "13", "precinct": "25"}, "6149 N HAMILTON AVE": {"ward": "40", "precinct": "18"}, "6149 N CAMPBELL AVE": {"ward": "40", "precinct": "4"}, "6149 S JUSTINE ST": {"ward": "16", "precinct": "31"}, "6149 N CENTRAL PARK AVE": {"ward": "50", "precinct": "24"}, "6149 N RAVENSWOOD AVE": {"ward": "40", "precinct": "27"}, "6149 S MASSASOIT AVE": {"ward": "13", "precinct": "17"}, "6149 S VERNON AVE": {"ward": "20", "precinct": "19"}, "6149 W BERENICE AVE": {"ward": "38", "precinct": "39"}, "6149 W BYRON ST": {"ward": "38", "precinct": "39"}, "6149 N SACRAMENTO AVE": {"ward": "50", "precinct": "17"}, "6149 N KEDVALE AVE": {"ward": "39", "precinct": "26"}, "6149 W GIDDINGS ST": {"ward": "38", "precinct": "25"}, "6149 S TALMAN AVE": {"ward": "16", "precinct": "18"}, "6149 N KILDARE AVE": {"ward": "39", "precinct": "40"}, "6149 S MCVICKER AVE": {"ward": "13", "precinct": "11"}, "6149 S KEATING AVE": {"ward": "13", "precinct": "25"}, "6149 N KARLOV AVE": {"ward": "39", "precinct": "26"}, "6149 N CLAREMONT AVE": {"ward": "40", "precinct": "39"}, "6149 N KNOX AVE": {"ward": "39", "precinct": "42"}, "6149 S SACRAMENTO AVE": {"ward": "16", "precinct": "13"}, "6149 S LANGLEY AVE": {"ward": "20", "precinct": "1"}, "6149 N LOWELL AVE": {"ward": "39", "precinct": "40"}, "6149 W FLETCHER ST": {"ward": "30", "precinct": "21"}, "6149 W GRAND AVE": {"ward": "36", "precinct": "5"}, "6149 S MEADE AVE": {"ward": "13", "precinct": "11"}, "6149 S CAMPBELL AVE": {"ward": "16", "precinct": "19"}, "6149 S NASHVILLE AVE": {"ward": "13", "precinct": "31"}, "6149 S WASHTENAW AVE": {"ward": "16", "precinct": "18"}, "6149 W HENDERSON ST": {"ward": "30", "precinct": "21"}, "6149 W LAWRENCE AVE": {"ward": "38", "precinct": "25"}, "6149 W 55TH ST": {"ward": "13", "precinct": "48"}, "6149 W GRACE ST": {"ward": "38", "precinct": "39"}, "6149 S MENARD AVE": {"ward": "13", "precinct": "17"}, "6149 S KILBOURN AVE": {"ward": "13", "precinct": "23"}, "6149 S KEELER AVE": {"ward": "23", "precinct": "10"}, "6149 W PETERSON AVE": {"ward": "45", "precinct": "42"}, "6149 S KENNETH AVE": {"ward": "13", "precinct": "23"}, "6149 N HARDING AVE": {"ward": "39", "precinct": "32"}, "6149 N LAWNDALE AVE": {"ward": "50", "precinct": "24"}, "6149 N OZARK AVE": {"ward": "41", "precinct": "18"}, "6149 N LEADER AVE": {"ward": "39", "precinct": "45"}, "6149 S SAINT LAWRENCE AVE": {"ward": "20", "precinct": "3"}, "6149 W 64TH PL": {"ward": "23", "precinct": "2"}, "6149 S CALIFORNIA AVE": {"ward": "16", "precinct": "17"}, "6149 S INDIANA AVE": {"ward": "20", "precinct": "7"}, "6149 S ROCKWELL ST": {"ward": "16", "precinct": "18"}, "6149 W ADDISON ST": {"ward": "36", "precinct": "18"}, "6149 N MEADE AVE": {"ward": "39", "precinct": "20"}, "6149 W 63RD PL": {"ward": "13", "precinct": "4"}, "6149 S ARTESIAN AVE": {"ward": "16", "precinct": "19"}, "6149 S CHAMPLAIN AVE": {"ward": "20", "precinct": "1"}, "6149 N ARTESIAN AVE": {"ward": "40", "precinct": "4"}, "6149 S KEDVALE AVE": {"ward": "23", "precinct": "10"}, "6149 N TALMAN AVE": {"ward": "40", "precinct": "10"}, "6149 S PARKSIDE AVE": {"ward": "13", "precinct": "26"}, "6149 W NELSON ST": {"ward": "30", "precinct": "13"}, "6149 S NATOMA AVE": {"ward": "13", "precinct": "31"}}