{"6906  S ARTESIAN AVE": {"precinct": "3", "ward": "17"}, "6906  W MEDILL AVE": {"precinct": "27", "ward": "36"}, "6906  S ADA ST": {"precinct": "21", "ward": "6"}, "6906  S BENNETT AVE": {"precinct": "28", "ward": "5"}, "6906  S PARNELL AVE": {"precinct": "5", "ward": "6"}, "6906  N WOLCOTT AVE": {"precinct": "10", "ward": "49"}, "6906  S PAXTON AVE": {"precinct": "38", "ward": "5"}, "6906  S OGLESBY AVE": {"precinct": "29", "ward": "5"}, "6906  N OTTAWA AVE": {"precinct": "42", "ward": "41"}, "6906  S KARLOV AVE": {"precinct": "46", "ward": "13"}, "6906  N LAKEWOOD AVE": {"precinct": "26", "ward": "49"}, "6906  S MICHIGAN AVE": {"precinct": "11", "ward": "6"}, "6906  S CORNELL AVE": {"precinct": "10", "ward": "5"}, "6906  N ALGONQUIN AVE": {"precinct": "9", "ward": "41"}, "6906  N CALIFORNIA AVE": {"precinct": "11", "ward": "50"}, "6906  S CHAPPEL AVE": {"precinct": "31", "ward": "5"}, "6906  S WABASH AVE": {"precinct": "9", "ward": "6"}, "6906  S CONSTANCE AVE": {"precinct": "28", "ward": "5"}, "6906  S KEDVALE AVE": {"precinct": "46", "ward": "13"}, "6906  S KIMBARK AVE": {"precinct": "30", "ward": "5"}, "6906  S INDIANA AVE": {"precinct": "11", "ward": "6"}, "6906  S WOODLAWN AVE": {"precinct": "30", "ward": "5"}, "6906  N ORIOLE AVE": {"precinct": "4", "ward": "41"}, "6906  S CLYDE AVE": {"precinct": "31", "ward": "5"}, "6906  N WAYNE AVE": {"precinct": "26", "ward": "49"}, "6906  N HAMILTON AVE": {"precinct": "35", "ward": "50"}, "6906  S CREGIER AVE": {"precinct": "28", "ward": "5"}, "6906  W DICKENS AVE": {"precinct": "30", "ward": "29"}, "6906  N ASHLAND AVE": {"precinct": "10", "ward": "49"}, "6906  N WAUKESHA AVE": {"precinct": "9", "ward": "41"}, "6906  N OLEANDER AVE": {"precinct": "4", "ward": "41"}}