{"7126 S LUELLA AVE": {"ward": "5", "precinct": "14"}, "7126 N MCALPIN AVE": {"ward": "41", "precinct": "47"}, "7126 S SAWYER AVE": {"ward": "17", "precinct": "1"}, "7126 S LAFAYETTE AVE": {"ward": "6", "precinct": "47"}, "7126 S CONSTANCE AVE": {"ward": "7", "precinct": "2"}, "7126 N OAKLEY AVE": {"ward": "50", "precinct": "7"}, "7126 S FAIRFIELD AVE": {"ward": "18", "precinct": "50"}, "7126 S WOOD ST": {"ward": "17", "precinct": "11"}, "7126 S DAMEN AVE": {"ward": "17", "precinct": "33"}, "7126 N NAGLE AVE": {"ward": "41", "precinct": "39"}, "7126 S SANGAMON ST": {"ward": "6", "precinct": "27"}, "7126 S GREENWOOD AVE": {"ward": "5", "precinct": "2"}, "7126 S RIDGEWAY AVE": {"ward": "13", "precinct": "19"}, "7126 S STEWART AVE": {"ward": "6", "precinct": "12"}, "7126 N OTTAWA AVE": {"ward": "41", "precinct": "42"}, "7126 S MAPLEWOOD AVE": {"ward": "18", "precinct": "48"}, "7126 S SOUTH CHICAGO AVE": {"ward": "5", "precinct": "12"}, "7126 S MOZART ST": {"ward": "18", "precinct": "50"}, "7126 W HIGHLAND AVE": {"ward": "41", "precinct": "11"}, "7126 S RICHMOND ST": {"ward": "18", "precinct": "27"}, "7126 W FARRAGUT AVE": {"ward": "41", "precinct": "3"}, "7126 N OSCEOLA AVE": {"ward": "41", "precinct": "44"}, "7126 S FRANCISCO AVE": {"ward": "18", "precinct": "27"}, "7126 S PAXTON AVE": {"ward": "5", "precinct": "6"}, "7126 S MILLARD AVE": {"ward": "13", "precinct": "19"}, "7126 S HERMITAGE AVE": {"ward": "17", "precinct": "11"}, "7126 N MELVINA AVE": {"ward": "41", "precinct": "39"}, "7126 S RHODES AVE": {"ward": "6", "precinct": "7"}, "7126 S AVERS AVE": {"ward": "13", "precinct": "19"}, "7126 S BELL AVE": {"ward": "18", "precinct": "5"}, "7126 S SPAULDING AVE": {"ward": "17", "precinct": "1"}, "7126 S LANGLEY AVE": {"ward": "6", "precinct": "30"}, "7126 S EBERHART AVE": {"ward": "6", "precinct": "48"}, "7126 S ELLIS AVE": {"ward": "5", "precinct": "2"}, "7126 N OZARK AVE": {"ward": "41", "precinct": "42"}, "7126 N OLCOTT AVE": {"ward": "41", "precinct": "4"}, "7126 S CHRISTIANA AVE": {"ward": "17", "precinct": "1"}, "7126 S MAY ST": {"ward": "6", "precinct": "22"}, "7126 S LAWNDALE AVE": {"ward": "13", "precinct": "19"}, "7126 S INDIANA AVE": {"ward": "6", "precinct": "32"}, "7126 S LOWE AVE": {"ward": "6", "precinct": "5"}, "7126 W 64TH ST": {"ward": "23", "precinct": "18"}, "7126 S WABASH AVE": {"ward": "6", "precinct": "32"}, "7126 S ARTESIAN AVE": {"ward": "18", "precinct": "48"}, "7126 W ARMITAGE AVE": {"ward": "29", "precinct": "23"}, "7126 W DEVON AVE": {"ward": "41", "precinct": "11"}, "7126 S MARSHFIELD AVE": {"ward": "17", "precinct": "32"}, "7126 S EAST END AVE": {"ward": "7", "precinct": "1"}, "7126 N ORIOLE AVE": {"ward": "41", "precinct": "4"}, "7126 S CHAMPLAIN AVE": {"ward": "6", "precinct": "30"}, "7126 W 63RD PL": {"ward": "23", "precinct": "18"}, "7126 S CLAREMONT AVE": {"ward": "18", "precinct": "5"}, "7126 N MANKATO AVE": {"ward": "41", "precinct": "47"}, "7126 S EUCLID AVE": {"ward": "5", "precinct": "36"}, "7126 S MICHIGAN AVE": {"ward": "6", "precinct": "32"}, "7126 S WOODLAWN AVE": {"ward": "5", "precinct": "2"}, "7126 N OVERHILL AVE": {"ward": "41", "precinct": "42"}, "7126 S WASHTENAW AVE": {"ward": "18", "precinct": "50"}, "7126 S VERNON AVE": {"ward": "6", "precinct": "48"}, "7126 S KEDZIE AVE": {"ward": "17", "precinct": "1"}, "7126 S UNIVERSITY AVE": {"ward": "5", "precinct": "2"}, "7126 N OLEANDER AVE": {"ward": "41", "precinct": "4"}, "7126 S ABERDEEN ST": {"ward": "6", "precinct": "27"}, "7126 N ODELL AVE": {"ward": "41", "precinct": "44"}, "7126 S PRINCETON AVE": {"ward": "6", "precinct": "12"}, "7126 S ROCKWELL ST": {"ward": "18", "precinct": "50"}}