{"7250 W LUNT AVE": {"ward": "41", "precinct": "44"}, "7250 N OCTAVIA AVE": {"ward": "41", "precinct": "44"}, "7250 S CAMPBELL AVE": {"ward": "18", "precinct": "48"}, "7250 W FARWELL AVE": {"ward": "41", "precinct": "10"}, "7250 S MICHIGAN AVE": {"ward": "6", "precinct": "32"}, "7250 N OLEANDER AVE": {"ward": "41", "precinct": "40"}, "7250 S WOOD ST": {"ward": "17", "precinct": "11"}, "7250 W RASCHER AVE": {"ward": "41", "precinct": "45"}, "7250 N CALIFORNIA AVE": {"ward": "50", "precinct": "1"}, "7250 S DAMEN AVE": {"ward": "17", "precinct": "37"}, "7250 S BLACKSTONE AVE": {"ward": "8", "precinct": "2"}, "7250 S HONORE ST": {"ward": "17", "precinct": "11"}, "7250 S MILLARD AVE": {"ward": "13", "precinct": "19"}, "7250 S WOLCOTT AVE": {"ward": "17", "precinct": "34"}, "7250 N OKETO AVE": {"ward": "41", "precinct": "44"}, "7250 S MAY ST": {"ward": "6", "precinct": "22"}, "7250 N OAKLEY AVE": {"ward": "50", "precinct": "8"}, "7250 W MYRTLE AVE": {"ward": "41", "precinct": "31"}, "7250 S CHAMPLAIN AVE": {"ward": "6", "precinct": "30"}, "7250 N RIDGE AVE": {"ward": "49", "precinct": "8"}, "7250 S EBERHART AVE": {"ward": "6", "precinct": "40"}, "7250 S CALIFORNIA AVE": {"ward": "18", "precinct": "49"}, "7250 S CALUMET AVE": {"ward": "6", "precinct": "48"}, "7250 S LOWE AVE": {"ward": "6", "precinct": "10"}, "7250 S SOUTH SHORE DR": {"ward": "7", "precinct": "6"}, "7250 N OSCEOLA AVE": {"ward": "41", "precinct": "44"}, "7250 W PALATINE AVE": {"ward": "41", "precinct": "37"}, "7250 S VERNON AVE": {"ward": "6", "precinct": "48"}, "7250 S PAULINA ST": {"ward": "17", "precinct": "32"}, "7250 N WESTERN AVE": {"ward": "50", "precinct": "9"}, "7250 N MEADE AVE": {"ward": "41", "precinct": "47"}, "7250 N CLAREMONT AVE": {"ward": "50", "precinct": "8"}, "7250 S CENTRAL PARK AVE": {"ward": "13", "precinct": "19"}, "7250 S EAST END AVE": {"ward": "7", "precinct": "1"}, "7250 S LAFAYETTE AVE": {"ward": "6", "precinct": "47"}, "7250 S EUCLID AVE": {"ward": "5", "precinct": "6"}, "7250 W BRYN MAWR AVE": {"ward": "41", "precinct": "43"}, "7250 S SACRAMENTO AVE": {"ward": "18", "precinct": "27"}, "7250 S CARPENTER ST": {"ward": "6", "precinct": "27"}, "7250 S KING DR": {"ward": "6", "precinct": "48"}, "7250 W GREENLEAF AVE": {"ward": "41", "precinct": "44"}, "7250 S MERRILL AVE": {"ward": "5", "precinct": "6"}, "7250 S LANGLEY AVE": {"ward": "6", "precinct": "30"}, "7250 S WINCHESTER AVE": {"ward": "17", "precinct": "34"}, "7250 S JEFFERY BLVD": {"ward": "5", "precinct": "6"}, "7250 W CLARENCE AVE": {"ward": "41", "precinct": "31"}, "7250 S PEORIA ST": {"ward": "6", "precinct": "25"}, "7250 N ORIOLE AVE": {"ward": "41", "precinct": "2"}, "7250 S OGLESBY AVE": {"ward": "5", "precinct": "14"}, "7250 S WASHTENAW AVE": {"ward": "18", "precinct": "49"}, "7250 W BELMONT AVE": {"ward": "29", "precinct": "32"}, "7250 S CORNELL AVE": {"ward": "7", "precinct": "1"}, "7250 S BENNETT AVE": {"ward": "7", "precinct": "2"}, "7250 S SANGAMON ST": {"ward": "6", "precinct": "25"}, "7250 S HARVARD AVE": {"ward": "6", "precinct": "10"}, "7250 S UNION AVE": {"ward": "6", "precinct": "25"}, "7250 S HAMLIN AVE": {"ward": "13", "precinct": "19"}, "7250 N ODELL AVE": {"ward": "41", "precinct": "44"}, "7250 S EVANS AVE": {"ward": "6", "precinct": "30"}, "7250 W COYLE AVE": {"ward": "41", "precinct": "10"}, "7250 S SAINT LAWRENCE AVE": {"ward": "6", "precinct": "40"}, "7250 S RHODES AVE": {"ward": "6", "precinct": "40"}, "7250 S RIDGEWAY AVE": {"ward": "13", "precinct": "19"}, "7250 S YATES AVE": {"ward": "7", "precinct": "5"}, "7250 W PRATT BLVD": {"ward": "41", "precinct": "10"}, "7250 W FITCH AVE": {"ward": "41", "precinct": "44"}, "7250 S OAKLEY AVE": {"ward": "18", "precinct": "5"}, "7250 S DORCHESTER AVE": {"ward": "8", "precinct": "1"}, "7250 S YALE AVE": {"ward": "6", "precinct": "10"}, "7250 N ROGERS AVE": {"ward": "49", "precinct": "15"}, "7250 S CLAREMONT AVE": {"ward": "18", "precinct": "5"}}