{"7603  S VERNON AVE": {"precinct": "43", "ward": "6"}, "7603  S MAY ST": {"precinct": "22", "ward": "17"}, "7603  S KINGSTON AVE": {"precinct": "12", "ward": "7"}, "7603  N GREENVIEW AVE": {"precinct": "32", "ward": "49"}, "7603  S PEORIA ST": {"precinct": "9", "ward": "17"}, "7603  S MORGAN ST": {"precinct": "2", "ward": "17"}, "7603  N SHERIDAN RD": {"precinct": "6", "ward": "49"}, "7603  S EUCLID AVE": {"precinct": "20", "ward": "8"}, "7603  S SEELEY AVE": {"precinct": "20", "ward": "18"}, "7603  S PAXTON AVE": {"precinct": "10", "ward": "7"}, "7603  S PRAIRIE AVE": {"precinct": "16", "ward": "6"}, "7603  S RIDGELAND AVE": {"precinct": "21", "ward": "8"}, "7603  S ESSEX AVE": {"precinct": "11", "ward": "7"}, "7603  S EMERALD AVE": {"precinct": "20", "ward": "6"}, "7603  S DREXEL AVE": {"precinct": "26", "ward": "8"}, "7603  S YATES AVE": {"precinct": "11", "ward": "7"}, "7603  S EAST END AVE": {"precinct": "21", "ward": "8"}, "7603  W PALATINE AVE": {"precinct": "8", "ward": "41"}, "7603  S COLES AVE": {"precinct": "14", "ward": "7"}, "7603  S LANGLEY AVE": {"precinct": "14", "ward": "6"}, "7603  W DEVON AVE": {"precinct": "8", "ward": "41"}, "7603  S KING DR": {"precinct": "43", "ward": "6"}}