{"7802 W THORNDALE AVE": {"ward": "41", "precinct": "41"}, "7802 S THROOP ST": {"ward": "17", "precinct": "27"}, "7802 S AVALON AVE": {"ward": "8", "precinct": "55"}, "7802 S CARPENTER ST": {"ward": "17", "precinct": "24"}, "7802 W ADDISON ST": {"ward": "38", "precinct": "27"}, "7802 S ASHLAND AVE": {"ward": "17", "precinct": "38"}, "7802 S LAFLIN ST": {"ward": "17", "precinct": "38"}, "7802 S PAULINA ST": {"ward": "17", "precinct": "38"}, "7802 S WINCHESTER AVE": {"ward": "17", "precinct": "41"}, "7802 S WOODLAWN AVE": {"ward": "8", "precinct": "55"}, "7802 W ARDMORE AVE": {"ward": "41", "precinct": "41"}, "7802 S MAY ST": {"ward": "17", "precinct": "24"}, "7802 S RIDGELAND AVE": {"ward": "8", "precinct": "13"}, "7802 S KINGSTON AVE": {"ward": "7", "precinct": "16"}, "7802 S BISHOP ST": {"ward": "17", "precinct": "27"}, "7802 S MORGAN ST": {"ward": "17", "precinct": "2"}, "7802 S MICHIGAN AVE": {"ward": "6", "precinct": "8"}, "7802 S ESSEX AVE": {"ward": "7", "precinct": "16"}, "7802 S MARSHFIELD AVE": {"ward": "17", "precinct": "38"}, "7802 S KENNETH AVE": {"ward": "18", "precinct": "46"}, "7802 S GREEN ST": {"ward": "17", "precinct": "10"}, "7802 S KOSTNER AVE": {"ward": "18", "precinct": "46"}, "7802 S COLFAX AVE": {"ward": "7", "precinct": "17"}, "7802 S SANGAMON ST": {"ward": "17", "precinct": "2"}, "7802 S ABERDEEN ST": {"ward": "17", "precinct": "24"}, "7802 W GLENLAKE AVE": {"ward": "41", "precinct": "18"}, "7802 S HONORE ST": {"ward": "17", "precinct": "41"}}