{"8127 S KOSTNER AVE": {"ward": "18", "precinct": "30"}, "8127 S EXCHANGE AVE": {"ward": "7", "precinct": "25"}, "8127 S HARPER AVE": {"ward": "8", "precinct": "6"}, "8127 S WOOD ST": {"ward": "21", "precinct": "15"}, "8127 S BLACKSTONE AVE": {"ward": "8", "precinct": "6"}, "8127 S COLES AVE": {"ward": "7", "precinct": "22"}, "8127 S SANGAMON ST": {"ward": "21", "precinct": "51"}, "8127 S SOUTH SHORE DR": {"ward": "7", "precinct": "22"}, "8127 S WENTWORTH AVE": {"ward": "21", "precinct": "53"}, "8127 S CLYDE AVE": {"ward": "8", "precinct": "36"}, "8127 S SAWYER AVE": {"ward": "18", "precinct": "8"}, "8127 S CHAPPEL AVE": {"ward": "8", "precinct": "53"}, "8127 S STATE ST": {"ward": "6", "precinct": "41"}, "8127 S OGLESBY AVE": {"ward": "7", "precinct": "23"}, "8127 S KINGSTON AVE": {"ward": "7", "precinct": "23"}, "8127 S KIMBARK AVE": {"ward": "8", "precinct": "29"}, "8127 S WASHTENAW AVE": {"ward": "18", "precinct": "41"}, "8127 S MERRILL AVE": {"ward": "8", "precinct": "36"}, "8127 S RHODES AVE": {"ward": "6", "precinct": "45"}, "8127 S JEFFERY BLVD": {"ward": "8", "precinct": "53"}, "8127 S SPAULDING AVE": {"ward": "18", "precinct": "21"}, "8127 S THROOP ST": {"ward": "21", "precinct": "28"}, "8127 S LOOMIS ST": {"ward": "21", "precinct": "47"}, "8127 S ELLIS AVE": {"ward": "8", "precinct": "14"}, "8127 S HERMITAGE AVE": {"ward": "21", "precinct": "15"}, "8127 S CHRISTIANA AVE": {"ward": "18", "precinct": "21"}, "8127 S BENNETT AVE": {"ward": "8", "precinct": "11"}, "8127 S WHIPPLE ST": {"ward": "18", "precinct": "8"}, "8127 S DAMEN AVE": {"ward": "17", "precinct": "20"}, "8127 S DREXEL AVE": {"ward": "8", "precinct": "18"}, "8127 S MARQUETTE AVE": {"ward": "7", "precinct": "24"}, "8127 S DANTE AVE": {"ward": "8", "precinct": "6"}, "8127 S PERRY AVE": {"ward": "21", "precinct": "31"}, "8127 S HOMAN AVE": {"ward": "18", "precinct": "21"}, "8127 S KOMENSKY AVE": {"ward": "18", "precinct": "25"}, "8127 S CRANDON AVE": {"ward": "8", "precinct": "7"}, "8127 S COMMERCIAL AVE": {"ward": "7", "precinct": "25"}, "8127 S COLFAX AVE": {"ward": "7", "precinct": "24"}, "8127 S CLAREMONT AVE": {"ward": "18", "precinct": "18"}, "8127 S CARPENTER ST": {"ward": "21", "precinct": "43"}, "8127 S INGLESIDE AVE": {"ward": "8", "precinct": "18"}, "8127 S MICHIGAN AVE": {"ward": "6", "precinct": "41"}, "8127 S WOODLAWN AVE": {"ward": "8", "precinct": "48"}, "8127 S PRAIRIE AVE": {"ward": "6", "precinct": "1"}, "8127 S BURNHAM AVE": {"ward": "7", "precinct": "24"}, "8127 S MARYLAND AVE": {"ward": "8", "precinct": "45"}, "8127 S GREEN ST": {"ward": "21", "precinct": "4"}, "8127 S TRIPP AVE": {"ward": "18", "precinct": "40"}, "8127 S STEWART AVE": {"ward": "21", "precinct": "53"}, "8127 W FOREST PRESERVE AVE": {"ward": "38", "precinct": "24"}, "8127 S ESCANABA AVE": {"ward": "7", "precinct": "25"}}